adastop/__init__.py
adastop/_version.py
adastop/cli.py
adastop/compare_agents.py
adastop/plotting.py
adastop-0.1.3.dist-info/licenses/LICENSE
adastop-0.1.3.dist-info/METADATA
adastop-0.1.3.dist-info/WHEEL
adastop-0.1.3.dist-info/entry_points.txt
adastop-0.1.3.dist-info/top_level.txt
adastop-0.1.3.dist-info/RECORD
