Metadata-Version: 2.4
Name: adastop
Version: 0.1.3
License: MIT
License-File: LICENSE
Requires-Dist: Click
Requires-Dist: numpy
Requires-Dist: matplotlib
Requires-Dist: pandas
Requires-Dist: tabulate
Dynamic: description
Dynamic: description-content-type
Dynamic: license
Dynamic: license-file
Dynamic: requires-dist
